ryport/__init__.py
ryport/utils.py
ryport/mysql/__init__.py
ryport/mysql/my_sql.py
ryport/pgsql/__init__.py
ryport/pgsql/postgres.py
ryport/report/__init__.py
ryport/report/csvw.py
ryport/report/xlsxw.py
ryport/xml_builder/__init__.py
ryport/xml_builder/builder.py
ryport/xml_builder/reader.py
ryport-1.0.16.dist-info/DESCRIPTION.rst
ryport-1.0.16.dist-info/METADATA
ryport-1.0.16.dist-info/RECORD
ryport-1.0.16.dist-info/WHEEL
ryport-1.0.16.dist-info/metadata.json
ryport-1.0.16.dist-info/top_level.txt
ryport-1.0.16.dist-info/zip-safe
