Metadata-Version: 2.0
Name: ryport
Version: 1.0.16
Summary: Softwrapper and reporting tool for Postgres
Home-page: https://github.com/IanDoarn/ryport
Author: Ian Doarn
Author-email: ian.doarn@zimmerbiomet.com
License: MIT
Platform: UNKNOWN
Classifier: Intended Audience :: Developers
Classifier: Operating System :: MacOS :: MacOS X
Classifier: Operating System :: Microsoft :: Windows
Classifier: Operating System :: POSIX :: Linux
Classifier: Programming Language :: Python :: 3.3
Classifier: Programming Language :: Python :: 3.4
Classifier: Programming Language :: Python :: 3.5
Classifier: Programming Language :: Python :: 3.6
Requires-Dist: XlsxWriter
Requires-Dist: lxml
Requires-Dist: mysql-connector-python
Requires-Dist: psycopg2
